uw_hfs/VERSION
uw_hfs/__init__.py
uw_hfs/dao.py
uw_hfs/idcard.py
uw_hfs/models.py
uw_hfs/test.py
uw_hfs/util.py
uw_hfs/resources/hfs/file/myuw/v1/eight
uw_hfs/resources/hfs/file/myuw/v1/invalidnetid
uw_hfs/resources/hfs/file/myuw/v1/javerage
uw_hfs/resources/hfs/file/myuw/v1/jbothell
uw_hfs/resources/hfs/file/myuw/v1/jerror
uw_hfs/resources/hfs/file/myuw/v1/jinternational
uw_hfs/resources/hfs/file/myuw/v1/jnew
uw_hfs/resources/hfs/file/myuw/v1/none
uw_hfs/tests/__init__.py
uw_hfs/tests/test_idcard.py
uw_restclients_hfs-1.0.7.dist-info/licenses/LICENSE
uw_restclients_hfs-1.0.7.dist-info/METADATA
uw_restclients_hfs-1.0.7.dist-info/WHEEL
uw_restclients_hfs-1.0.7.dist-info/top_level.txt
uw_restclients_hfs-1.0.7.dist-info/RECORD
